{
  "_class": "symbolInstance",
  "booleanOperation": 0,
  "do_objectID": "A090FD30-8F96-4DD1-AD8F-1295A5575AC3",
  "exportOptions": {
    "_class": "exportOptions",
    "do_objectID": "25B857F3-ED1E-42BA-A4CD-ADF8906310DF",
    "exportFormats": [
    ],
    "includedLayerIds": [
    ],
    "layerOptions": 0,
    "shouldTrim": false
  },
  "frame": {
    "_class": "rect",
    "constrainProportions": false,
    "do_objectID": "890786D6-AC92-4833-83DC-8209CA823E26",
    "height": 16,
    "width": 16,
    "x": 0,
    "y": 1
  },
  "horizontalSpacing": 0,
  "isFixedToViewport": false,
  "isFlippedHorizontal": false,
  "isFlippedVertical": false,
  "isLocked": false,
  "isVisible": true,
  "layerListExpandedType": 0,
  "name": "Icon/UI/search--glyph",
  "nameIsFixed": false,
  "overrideValues": [
  ],
  "resizingConstraint": 63,
  "resizingType": 0,
  "rotation": 360,
  "scale": 1,
  "shouldBreakMaskChain": false,
  "style": {
    "_class": "style",
    "do_objectID": "39E71CE4-F3F8-4D00-9955-844CB8D55306",
    "endMarkerType": 0,
    "miterLimit": 10,
    "startMarkerType": 0,
    "windingRule": 1
  },
  "symbolID": "3AFD71FB-A3DB-463C-AFA4-53E87FFAB45A",
  "verticalSpacing": 0
}