{
  "_class": "symbolInstance",
  "booleanOperation": 0,
  "do_objectID": "B7212C41-E4D6-4E56-B02C-9E83F2E10227",
  "exportOptions": {
    "_class": "exportOptions",
    "do_objectID": "B9C42109-8180-4144-B857-68FA643BA772",
    "exportFormats": [
    ],
    "includedLayerIds": [
    ],
    "layerOptions": 0,
    "shouldTrim": false
  },
  "frame": {
    "_class": "rect",
    "constrainProportions": false,
    "do_objectID": "41B7AE1D-7F13-4F6A-A71D-BDD0FE72D050",
    "height": 49,
    "width": 320,
    "x": 0,
    "y": 0
  },
  "horizontalSpacing": 0,
  "isFixedToViewport": false,
  "isFlippedHorizontal": false,
  "isFlippedVertical": false,
  "isLocked": false,
  "isVisible": true,
  "layerListExpandedType": 0,
  "name": "/RNZ/ Header 320",
  "nameIsFixed": false,
  "overrideValues": [
  ],
  "resizingConstraint": 63,
  "resizingType": 0,
  "rotation": 0,
  "scale": 1,
  "shouldBreakMaskChain": false,
  "style": {
    "_class": "style",
    "do_objectID": "CA479B7D-29E8-4CC5-A262-6A158DA8A60C",
    "endMarkerType": 0,
    "miterLimit": 10,
    "startMarkerType": 0,
    "windingRule": 1
  },
  "symbolID": "9F816FF5-10F2-478C-92C5-58AD0FB5EA38",
  "verticalSpacing": 0
}